[
  { "name": "sketch", "title": "Sketches" },
  { "name": "radials", "title": "Radials" },
  { "name": "shape-bounds", "title": "Shape bounds" },
  { "name": "containers", "title": "Containers" },
  { "name": "texts", "title": "Text", "css": ["/components/css/style.css"]},
  { "name": "sprites", "title": "Sprite animation" },
  { "name": "matrix", "title": "Animation base on matrixes" },
  { "name": "movement", "title": "Animation base on Cubic-Bezier" },
  { "name": "collisions", "title": "Collisions detection" },
  { "name": "raster-filters", "title": "Raster filters", "css": ["/index.css"] },
  { "name": "readme", "title": "Example from readme" },
  { "name": "dynamic-renderer", "title": "Dynamic Canvas", "css": ["/index.css"] }
]